EUKulele/EUKulele-env.yaml
EUKulele/EUKulele_config.py
EUKulele/EUKulele_main.py
EUKulele/__init__.py
EUKulele/busco_runner.py
EUKulele/config.yaml
EUKulele/config_full.yaml
EUKulele/download_database.py
EUKulele/manage_steps.py
EUKulele/tax_placement.py
EUKulele/visualize_results.py
EUKulele/EUKulele.egg-info/PKG-INFO
EUKulele/EUKulele.egg-info/SOURCES.txt
EUKulele/EUKulele.egg-info/dependency_links.txt
EUKulele/EUKulele.egg-info/requires.txt
EUKulele/EUKulele.egg-info/top_level.txt
EUKulele/__pycache__/EUKulele_config.cpython-36.pyc
EUKulele/__pycache__/EUKulele_main.cpython-36.pyc
EUKulele/__pycache__/__init__.cpython-36.pyc
EUKulele/__pycache__/tax_placement.cpython-36.pyc
EUKulele/__pycache__/visualize_results.cpython-36.pyc
EUKulele/static/VERSION
EUKulele/static/__init__.py
EUKulele/static/busco_config.ini
EUKulele/static/config.ini
EUKulele/static/config.yaml
EUKulele/static/reference_url.yaml
EUKulele/static/tax-cutoffs.yaml
EUKulele-2.1.0.data/scripts/EUKulele
EUKulele-2.1.0.data/scripts/after_job.sh
EUKulele-2.1.0.data/scripts/concatenate_busco.sh
EUKulele-2.1.0.data/scripts/configure_busco.sh
EUKulele-2.1.0.data/scripts/coordinate_batch.sh
EUKulele-2.1.0.data/scripts/create_protein_table.py
EUKulele-2.1.0.data/scripts/download_database.sh
EUKulele-2.1.0.data/scripts/install_dependencies.sh
EUKulele-2.1.0.data/scripts/remove_newlines.sh
EUKulele-2.1.0.data/scripts/run_busco.sh
scripts/__init__.py
scripts/after_job.sh
scripts/concatenate_busco.sh
scripts/configure_busco.sh
scripts/coordinate_batch.sh
scripts/create_protein_table.py
scripts/create_protein_table_sandbox.py
scripts/diamond_aligner.sh
scripts/download_database.sh
scripts/install_dependencies.sh
scripts/mag_stats.py
scripts/names_to_reads.py
scripts/process-output.R
scripts/query_busco.py
scripts/remove_newlines.sh
scripts/run_busco.sh
scripts/submit-EUKulele.sh
EUKulele-2.1.0.dist-info/LICENSE
EUKulele-2.1.0.dist-info/METADATA
EUKulele-2.1.0.dist-info/PKG-INFO-CHR
EUKulele-2.1.0.dist-info/WHEEL
EUKulele-2.1.0.dist-info/top_level.txt
EUKulele-2.1.0.dist-info/RECORD
