Metadata-Version: 2.1
Name: EUKulele
Version: 2.1.0
Summary: A package to make the process of taxonomically classifying microbial eukaryotes easier.
Home-page: https://github.com/AlexanderLabWHOI/EUKulele
Author: Arianna Krinos
Author-email: akrinos@mit.edu
License: MIT
Keywords: eukaryotic taxonomy classification
License-File: LICENSE
Requires-Dist: numpy
Requires-Dist: biopython
Requires-Dist: pandas
Requires-Dist: seaborn
Requires-Dist: chardet
Requires-Dist: multiprocess
Requires-Dist: joblib
Requires-Dist: ujson
Requires-Dist: python-coveralls
Requires-Dist: pyyaml
Requires-Dist: matplotlib
Requires-Dist: pytest-cov
Requires-Dist: pytest-xdist
Requires-Dist: sphinxcontrib-bibtex ==1.0.0
